co_location/__init__.py
co_location/co_location.py
co_location/server.py
co_location/cfg_load/__init__.py
co_location/cfg_load/conf.py
co_location/internals/__init__.py
co_location/internals/_functions.py
co_location/kubernetes/__init__.py
co_location/kubernetes/_workflow.py
co_location/metricsCollectors/__init__.py
co_location/metricsCollectors/_clusterInformation.py
co_location/metricsCollectors/_clusterStatus.py
co_location/metricsCollectors/_functionsMetricsInterferences.py
test/__init__.py
test/test_collocation.py
co_location-1.5.4.dist-info/LICENSE.txt
co_location-1.5.4.dist-info/METADATA
co_location-1.5.4.dist-info/WHEEL
co_location-1.5.4.dist-info/top_level.txt
co_location-1.5.4.dist-info/RECORD
