Metadata-Version: 2.1
Name: co-location
Version: 1.5.4
Summary: Physcis project. Kubernertes Collocation library
Download-URL: https://github.com/physics-faas/co-location/archive/refs/tags/v.1.5.4.tar.gz
Author: Ainhoa Azqueta-Alzúaz
Author-email: aazqueta@fi.upm.es
License: MIT
Requires-Python: >=3.7
License-File: LICENSE.txt
Requires-Dist: kubernetes
Requires-Dist: prometheus-api-client
Requires-Dist: prometheus-client
